hund/__init__.py
hund-0.1.2.dist-info/METADATA
hund-0.1.2.dist-info/WHEEL
hund-0.1.2.dist-info/licenses/LICENSE.txt
hund-0.1.2.dist-info/RECORD
