Metadata-Version: 2.1
Name: hund
Version: 0.1.2
Summary: Implement a function that applies Hund's rules to a given electronic (atomic) configuration.
Project-URL: Source, https://github.com/proggy/hund
Project-URL: Homepage, https://github.com/proggy/hund
Project-URL: Bug Tracker, https://github.com/proggy/hund/issues
Author-email: Daniel Jung <proggy-contact@mailbox.org>
Maintainer-email: Daniel Jung <proggy-contact@mailbox.org>
License-File: LICENSE.txt
Classifier: License :: OSI Approved :: GNU General Public License v2 (GPLv2)
Classifier: Operating System :: OS Independent
Classifier: Programming Language :: Python :: 3
Requires-Python: >=3.7
